LICENSE
setup.py
departments/__init__.py
departments/admin.py
departments/apps.py
departments/models.py
departments/tests.py
departments/views.py
departments/common/__init__.py
departments/common/config.py
departments/forms/__init__.py
departments/forms/forms.py
departments/migrations/0001_initial.py
departments/migrations/0002_auto_20221012_1403.py
departments/migrations/__init__.py
departments/utils/__init__.py
departments/utils/department_funcs.py
departments/utils/error_response.py
departments/utils/position_funcs.py
departments/utils/request_test.py
departments/utils/role_funcs.py
departments/views/__init__.py
departments/views/department.py
departments/views/position.py
departments/views/roles.py
django_simple_org.egg-info/PKG-INFO
django_simple_org.egg-info/SOURCES.txt
django_simple_org.egg-info/dependency_links.txt
django_simple_org.egg-info/top_level.txt