Metadata-Version: 2.1
Name: django-simple-org
Version: 0.3.5
Summary: 组织架构
Author: yuwenyang
Author-email: ywyhpnn@126.com
License: UNKNOWN
Platform: UNKNOWN
Classifier: Programming Language :: Python :: 3
Requires-Python: >=3
License-File: LICENSE
